[
  {
    "apiVersion": "apiextensions.k8s.io/v1",
    "kind": "CustomResourceDefinition",
    "metadata": {
      "annotations": {
        "helm.sh/resource-policy": "keep"
      },
      "creationTimestamp": null,
      "labels": {
        "app.kubernetes.io/name": "google.kubeform.com",
        "app.kubernetes.io/part-of": "kubeform.com"
      },
      "name": "accessapprovalsettings.organization.google.kubeform.com"
    },
    "spec": {
      "group": "organization.google.kubeform.com",
      "names": {
        "kind": "AccessApprovalSettings",
        "listKind": "AccessApprovalSettingsList",
        "plural": "accessapprovalsettings",
        "singular": "accessapprovalsettings"
      },
      "scope": "Namespaced",
      "versions": [
        {
          "additionalPrinterColumns": [
            {
              "jsonPath": ".status.phase",
              "name": "Phase",
              "type": "string"
            }
          ],
          "name": "v1alpha1",
          "schema": {
            "openAPIV3Schema": {
              "properties": {
                "apiVersion": {
                  "type": "string"
                },
                "kind": {
                  "type": "string"
                },
                "metadata": {
                  "type": "object"
                },
                "spec": {
                  "properties": {
                    "backendRef": {
                      "properties": {
                        "name": {
                          "type": "string"
                        }
                      },
                      "type": "object"
                    },
                    "providerRef": {
                      "properties": {
                        "name": {
                          "type": "string"
                        }
                      },
                      "type": "object"
                    },
                    "resource": {
                      "properties": {
                        "enrolledAncestor": {
                          "type": "boolean"
                        },
                        "enrolledServices": {
                          "items": {
                            "properties": {
                              "cloudProduct": {
                                "type": "string"
                              },
                              "enrollmentLevel": {
                                "type": "string"
                              }
                            },
                            "required": [
                              "cloudProduct"
                            ],
                            "type": "object"
                          },
                          "type": "array"
                        },
                        "id": {
                          "type": "string"
                        },
                        "name": {
                          "type": "string"
                        },
                        "notificationEmails": {
                          "items": {
                            "type": "string"
                          },
                          "maxItems": 50,
                          "type": "array"
                        },
                        "organizationID": {
                          "type": "string"
                        },
                        "timeouts": {
                          "properties": {
                            "create": {
                              "format": "int64",
                              "type": "integer"
                            },
                            "default": {
                              "format": "int64",
                              "type": "integer"
                            },
                            "delete": {
                              "format": "int64",
                              "type": "integer"
                            },
                            "read": {
                              "format": "int64",
                              "type": "integer"
                            },
                            "update": {
                              "format": "int64",
                              "type": "integer"
                            }
                          },
                          "type": "object"
                        }
                      },
                      "required": [
                        "enrolledServices",
                        "organizationID"
                      ],
                      "type": "object"
                    },
                    "state": {
                      "properties": {
                        "enrolledAncestor": {
                          "type": "boolean"
                        },
                        "enrolledServices": {
                          "items": {
                            "properties": {
                              "cloudProduct": {
                                "type": "string"
                              },
                              "enrollmentLevel": {
                                "type": "string"
                              }
                            },
                            "required": [
                              "cloudProduct"
                            ],
                            "type": "object"
                          },
                          "type": "array"
                        },
                        "id": {
                          "type": "string"
                        },
                        "name": {
                          "type": "string"
                        },
                        "notificationEmails": {
                          "items": {
                            "type": "string"
                          },
                          "maxItems": 50,
                          "type": "array"
                        },
                        "organizationID": {
                          "type": "string"
                        },
                        "timeouts": {
                          "properties": {
                            "create": {
                              "format": "int64",
                              "type": "integer"
                            },
                            "default": {
                              "format": "int64",
                              "type": "integer"
                            },
                            "delete": {
                              "format": "int64",
                              "type": "integer"
                            },
                            "read": {
                              "format": "int64",
                              "type": "integer"
                            },
                            "update": {
                              "format": "int64",
                              "type": "integer"
                            }
                          },
                          "type": "object"
                        }
                      },
                      "required": [
                        "enrolledServices",
                        "organizationID"
                      ],
                      "type": "object"
                    },
                    "terminationPolicy": {
                      "enum": [
                        "Delete",
                        "DoNotTerminate"
                      ],
                      "type": "string"
                    },
                    "updatePolicy": {
                      "enum": [
                        "Destroy",
                        "DoNotDestroy"
                      ],
                      "type": "string"
                    }
                  },
                  "required": [
                    "providerRef",
                    "resource"
                  ],
                  "type": "object"
                },
                "status": {
                  "properties": {
                    "conditions": {
                      "items": {
                        "properties": {
                          "lastTransitionTime": {
                            "format": "date-time",
                            "type": "string"
                          },
                          "message": {
                            "type": "string"
                          },
                          "observedGeneration": {
                            "format": "int64",
                            "type": "integer"
                          },
                          "reason": {
                            "type": "string"
                          },
                          "status": {
                            "type": "string"
                          },
                          "type": {
                            "type": "string"
                          }
                        },
                        "required": [
                          "lastTransitionTime",
                          "message",
                          "reason",
                          "status",
                          "type"
                        ],
                        "type": "object"
                      },
                      "type": "array"
                    },
                    "observedGeneration": {
                      "format": "int64",
                      "type": "integer"
                    },
                    "phase": {
                      "type": "string"
                    }
                  },
                  "type": "object"
                }
              },
              "type": "object"
            }
          },
          "served": true,
          "storage": true,
          "subresources": {
            "status": {}
          }
        }
      ]
    }
  },
  {
    "apiVersion": "apiextensions.k8s.io/v1",
    "kind": "CustomResourceDefinition",
    "metadata": {
      "annotations": {
        "helm.sh/resource-policy": "keep"
      },
      "creationTimestamp": null,
      "labels": {
        "app.kubernetes.io/name": "google.kubeform.com",
        "app.kubernetes.io/part-of": "kubeform.com"
      },
      "name": "iamauditconfigs.organization.google.kubeform.com"
    },
    "spec": {
      "group": "organization.google.kubeform.com",
      "names": {
        "kind": "IamAuditConfig",
        "listKind": "IamAuditConfigList",
        "plural": "iamauditconfigs",
        "singular": "iamauditconfig"
      },
      "scope": "Namespaced",
      "versions": [
        {
          "additionalPrinterColumns": [
            {
              "jsonPath": ".status.phase",
              "name": "Phase",
              "type": "string"
            }
          ],
          "name": "v1alpha1",
          "schema": {
            "openAPIV3Schema": {
              "properties": {
                "apiVersion": {
                  "type": "string"
                },
                "kind": {
                  "type": "string"
                },
                "metadata": {
                  "type": "object"
                },
                "spec": {
                  "properties": {
                    "backendRef": {
                      "properties": {
                        "name": {
                          "type": "string"
                        }
                      },
                      "type": "object"
                    },
                    "providerRef": {
                      "properties": {
                        "name": {
                          "type": "string"
                        }
                      },
                      "type": "object"
                    },
                    "resource": {
                      "properties": {
                        "auditLogConfig": {
                          "items": {
                            "properties": {
                              "exemptedMembers": {
                                "items": {
                                  "type": "string"
                                },
                                "type": "array"
                              },
                              "logType": {
                                "type": "string"
                              }
                            },
                            "required": [
                              "logType"
                            ],
                            "type": "object"
                          },
                          "type": "array"
                        },
                        "etag": {
                          "type": "string"
                        },
                        "id": {
                          "type": "string"
                        },
                        "orgID": {
                          "type": "string"
                        },
                        "service": {
                          "type": "string"
                        }
                      },
                      "required": [
                        "auditLogConfig",
                        "orgID",
                        "service"
                      ],
                      "type": "object"
                    },
                    "state": {
                      "properties": {
                        "auditLogConfig": {
                          "items": {
                            "properties": {
                              "exemptedMembers": {
                                "items": {
                                  "type": "string"
                                },
                                "type": "array"
                              },
                              "logType": {
                                "type": "string"
                              }
                            },
                            "required": [
                              "logType"
                            ],
                            "type": "object"
                          },
                          "type": "array"
                        },
                        "etag": {
                          "type": "string"
                        },
                        "id": {
                          "type": "string"
                        },
                        "orgID": {
                          "type": "string"
                        },
                        "service": {
                          "type": "string"
                        }
                      },
                      "required": [
                        "auditLogConfig",
                        "orgID",
                        "service"
                      ],
                      "type": "object"
                    },
                    "terminationPolicy": {
                      "enum": [
                        "Delete",
                        "DoNotTerminate"
                      ],
                      "type": "string"
                    },
                    "updatePolicy": {
                      "enum": [
                        "Destroy",
                        "DoNotDestroy"
                      ],
                      "type": "string"
                    }
                  },
                  "required": [
                    "providerRef",
                    "resource"
                  ],
                  "type": "object"
                },
                "status": {
                  "properties": {
                    "conditions": {
                      "items": {
                        "properties": {
                          "lastTransitionTime": {
                            "format": "date-time",
                            "type": "string"
                          },
                          "message": {
                            "type": "string"
                          },
                          "observedGeneration": {
                            "format": "int64",
                            "type": "integer"
                          },
                          "reason": {
                            "type": "string"
                          },
                          "status": {
                            "type": "string"
                          },
                          "type": {
                            "type": "string"
                          }
                        },
                        "required": [
                          "lastTransitionTime",
                          "message",
                          "reason",
                          "status",
                          "type"
                        ],
                        "type": "object"
                      },
                      "type": "array"
                    },
                    "observedGeneration": {
                      "format": "int64",
                      "type": "integer"
                    },
                    "phase": {
                      "type": "string"
                    }
                  },
                  "type": "object"
                }
              },
              "type": "object"
            }
          },
          "served": true,
          "storage": true,
          "subresources": {
            "status": {}
          }
        }
      ]
    }
  },
  {
    "apiVersion": "apiextensions.k8s.io/v1",
    "kind": "CustomResourceDefinition",
    "metadata": {
      "annotations": {
        "helm.sh/resource-policy": "keep"
      },
      "creationTimestamp": null,
      "labels": {
        "app.kubernetes.io/name": "google.kubeform.com",
        "app.kubernetes.io/part-of": "kubeform.com"
      },
      "name": "iambindings.organization.google.kubeform.com"
    },
    "spec": {
      "group": "organization.google.kubeform.com",
      "names": {
        "kind": "IamBinding",
        "listKind": "IamBindingList",
        "plural": "iambindings",
        "singular": "iambinding"
      },
      "scope": "Namespaced",
      "versions": [
        {
          "additionalPrinterColumns": [
            {
              "jsonPath": ".status.phase",
              "name": "Phase",
              "type": "string"
            }
          ],
          "name": "v1alpha1",
          "schema": {
            "openAPIV3Schema": {
              "properties": {
                "apiVersion": {
                  "type": "string"
                },
                "kind": {
                  "type": "string"
                },
                "metadata": {
                  "type": "object"
                },
                "spec": {
                  "properties": {
                    "backendRef": {
                      "properties": {
                        "name": {
                          "type": "string"
                        }
                      },
                      "type": "object"
                    },
                    "providerRef": {
                      "properties": {
                        "name": {
                          "type": "string"
                        }
                      },
                      "type": "object"
                    },
                    "resource": {
                      "properties": {
                        "condition": {
                          "properties": {
                            "description": {
                              "type": "string"
                            },
                            "expression": {
                              "type": "string"
                            },
                            "title": {
                              "type": "string"
                            }
                          },
                          "required": [
                            "expression",
                            "title"
                          ],
                          "type": "object"
                        },
                        "etag": {
                          "type": "string"
                        },
                        "id": {
                          "type": "string"
                        },
                        "members": {
                          "items": {
                            "type": "string"
                          },
                          "type": "array"
                        },
                        "orgID": {
                          "type": "string"
                        },
                        "role": {
                          "type": "string"
                        }
                      },
                      "required": [
                        "members",
                        "orgID",
                        "role"
                      ],
                      "type": "object"
                    },
                    "state": {
                      "properties": {
                        "condition": {
                          "properties": {
                            "description": {
                              "type": "string"
                            },
                            "expression": {
                              "type": "string"
                            },
                            "title": {
                              "type": "string"
                            }
                          },
                          "required": [
                            "expression",
                            "title"
                          ],
                          "type": "object"
                        },
                        "etag": {
                          "type": "string"
                        },
                        "id": {
                          "type": "string"
                        },
                        "members": {
                          "items": {
                            "type": "string"
                          },
                          "type": "array"
                        },
                        "orgID": {
                          "type": "string"
                        },
                        "role": {
                          "type": "string"
                        }
                      },
                      "required": [
                        "members",
                        "orgID",
                        "role"
                      ],
                      "type": "object"
                    },
                    "terminationPolicy": {
                      "enum": [
                        "Delete",
                        "DoNotTerminate"
                      ],
                      "type": "string"
                    },
                    "updatePolicy": {
                      "enum": [
                        "Destroy",
                        "DoNotDestroy"
                      ],
                      "type": "string"
                    }
                  },
                  "required": [
                    "providerRef",
                    "resource"
                  ],
                  "type": "object"
                },
                "status": {
                  "properties": {
                    "conditions": {
                      "items": {
                        "properties": {
                          "lastTransitionTime": {
                            "format": "date-time",
                            "type": "string"
                          },
                          "message": {
                            "type": "string"
                          },
                          "observedGeneration": {
                            "format": "int64",
                            "type": "integer"
                          },
                          "reason": {
                            "type": "string"
                          },
                          "status": {
                            "type": "string"
                          },
                          "type": {
                            "type": "string"
                          }
                        },
                        "required": [
                          "lastTransitionTime",
                          "message",
                          "reason",
                          "status",
                          "type"
                        ],
                        "type": "object"
                      },
                      "type": "array"
                    },
                    "observedGeneration": {
                      "format": "int64",
                      "type": "integer"
                    },
                    "phase": {
                      "type": "string"
                    }
                  },
                  "type": "object"
                }
              },
              "type": "object"
            }
          },
          "served": true,
          "storage": true,
          "subresources": {
            "status": {}
          }
        }
      ]
    }
  },
  {
    "apiVersion": "apiextensions.k8s.io/v1",
    "kind": "CustomResourceDefinition",
    "metadata": {
      "annotations": {
        "helm.sh/resource-policy": "keep"
      },
      "creationTimestamp": null,
      "labels": {
        "app.kubernetes.io/name": "google.kubeform.com",
        "app.kubernetes.io/part-of": "kubeform.com"
      },
      "name": "iamcustomroles.organization.google.kubeform.com"
    },
    "spec": {
      "group": "organization.google.kubeform.com",
      "names": {
        "kind": "IamCustomRole",
        "listKind": "IamCustomRoleList",
        "plural": "iamcustomroles",
        "singular": "iamcustomrole"
      },
      "scope": "Namespaced",
      "versions": [
        {
          "additionalPrinterColumns": [
            {
              "jsonPath": ".status.phase",
              "name": "Phase",
              "type": "string"
            }
          ],
          "name": "v1alpha1",
          "schema": {
            "openAPIV3Schema": {
              "properties": {
                "apiVersion": {
                  "type": "string"
                },
                "kind": {
                  "type": "string"
                },
                "metadata": {
                  "type": "object"
                },
                "spec": {
                  "properties": {
                    "backendRef": {
                      "properties": {
                        "name": {
                          "type": "string"
                        }
                      },
                      "type": "object"
                    },
                    "providerRef": {
                      "properties": {
                        "name": {
                          "type": "string"
                        }
                      },
                      "type": "object"
                    },
                    "resource": {
                      "properties": {
                        "deleted": {
                          "type": "boolean"
                        },
                        "description": {
                          "type": "string"
                        },
                        "id": {
                          "type": "string"
                        },
                        "name": {
                          "type": "string"
                        },
                        "orgID": {
                          "type": "string"
                        },
                        "permissions": {
                          "items": {
                            "type": "string"
                          },
                          "minItems": 1,
                          "type": "array"
                        },
                        "roleID": {
                          "type": "string"
                        },
                        "stage": {
                          "type": "string"
                        },
                        "title": {
                          "type": "string"
                        }
                      },
                      "required": [
                        "orgID",
                        "permissions",
                        "roleID",
                        "title"
                      ],
                      "type": "object"
                    },
                    "state": {
                      "properties": {
                        "deleted": {
                          "type": "boolean"
                        },
                        "description": {
                          "type": "string"
                        },
                        "id": {
                          "type": "string"
                        },
                        "name": {
                          "type": "string"
                        },
                        "orgID": {
                          "type": "string"
                        },
                        "permissions": {
                          "items": {
                            "type": "string"
                          },
                          "minItems": 1,
                          "type": "array"
                        },
                        "roleID": {
                          "type": "string"
                        },
                        "stage": {
                          "type": "string"
                        },
                        "title": {
                          "type": "string"
                        }
                      },
                      "required": [
                        "orgID",
                        "permissions",
                        "roleID",
                        "title"
                      ],
                      "type": "object"
                    },
                    "terminationPolicy": {
                      "enum": [
                        "Delete",
                        "DoNotTerminate"
                      ],
                      "type": "string"
                    },
                    "updatePolicy": {
                      "enum": [
                        "Destroy",
                        "DoNotDestroy"
                      ],
                      "type": "string"
                    }
                  },
                  "required": [
                    "providerRef",
                    "resource"
                  ],
                  "type": "object"
                },
                "status": {
                  "properties": {
                    "conditions": {
                      "items": {
                        "properties": {
                          "lastTransitionTime": {
                            "format": "date-time",
                            "type": "string"
                          },
                          "message": {
                            "type": "string"
                          },
                          "observedGeneration": {
                            "format": "int64",
                            "type": "integer"
                          },
                          "reason": {
                            "type": "string"
                          },
                          "status": {
                            "type": "string"
                          },
                          "type": {
                            "type": "string"
                          }
                        },
                        "required": [
                          "lastTransitionTime",
                          "message",
                          "reason",
                          "status",
                          "type"
                        ],
                        "type": "object"
                      },
                      "type": "array"
                    },
                    "observedGeneration": {
                      "format": "int64",
                      "type": "integer"
                    },
                    "phase": {
                      "type": "string"
                    }
                  },
                  "type": "object"
                }
              },
              "type": "object"
            }
          },
          "served": true,
          "storage": true,
          "subresources": {
            "status": {}
          }
        }
      ]
    }
  },
  {
    "apiVersion": "apiextensions.k8s.io/v1",
    "kind": "CustomResourceDefinition",
    "metadata": {
      "annotations": {
        "helm.sh/resource-policy": "keep"
      },
      "creationTimestamp": null,
      "labels": {
        "app.kubernetes.io/name": "google.kubeform.com",
        "app.kubernetes.io/part-of": "kubeform.com"
      },
      "name": "iammembers.organization.google.kubeform.com"
    },
    "spec": {
      "group": "organization.google.kubeform.com",
      "names": {
        "kind": "IamMember",
        "listKind": "IamMemberList",
        "plural": "iammembers",
        "singular": "iammember"
      },
      "scope": "Namespaced",
      "versions": [
        {
          "additionalPrinterColumns": [
            {
              "jsonPath": ".status.phase",
              "name": "Phase",
              "type": "string"
            }
          ],
          "name": "v1alpha1",
          "schema": {
            "openAPIV3Schema": {
              "properties": {
                "apiVersion": {
                  "type": "string"
                },
                "kind": {
                  "type": "string"
                },
                "metadata": {
                  "type": "object"
                },
                "spec": {
                  "properties": {
                    "backendRef": {
                      "properties": {
                        "name": {
                          "type": "string"
                        }
                      },
                      "type": "object"
                    },
                    "providerRef": {
                      "properties": {
                        "name": {
                          "type": "string"
                        }
                      },
                      "type": "object"
                    },
                    "resource": {
                      "properties": {
                        "condition": {
                          "properties": {
                            "description": {
                              "type": "string"
                            },
                            "expression": {
                              "type": "string"
                            },
                            "title": {
                              "type": "string"
                            }
                          },
                          "required": [
                            "expression",
                            "title"
                          ],
                          "type": "object"
                        },
                        "etag": {
                          "type": "string"
                        },
                        "id": {
                          "type": "string"
                        },
                        "member": {
                          "type": "string"
                        },
                        "orgID": {
                          "type": "string"
                        },
                        "role": {
                          "type": "string"
                        }
                      },
                      "required": [
                        "member",
                        "orgID",
                        "role"
                      ],
                      "type": "object"
                    },
                    "state": {
                      "properties": {
                        "condition": {
                          "properties": {
                            "description": {
                              "type": "string"
                            },
                            "expression": {
                              "type": "string"
                            },
                            "title": {
                              "type": "string"
                            }
                          },
                          "required": [
                            "expression",
                            "title"
                          ],
                          "type": "object"
                        },
                        "etag": {
                          "type": "string"
                        },
                        "id": {
                          "type": "string"
                        },
                        "member": {
                          "type": "string"
                        },
                        "orgID": {
                          "type": "string"
                        },
                        "role": {
                          "type": "string"
                        }
                      },
                      "required": [
                        "member",
                        "orgID",
                        "role"
                      ],
                      "type": "object"
                    },
                    "terminationPolicy": {
                      "enum": [
                        "Delete",
                        "DoNotTerminate"
                      ],
                      "type": "string"
                    },
                    "updatePolicy": {
                      "enum": [
                        "Destroy",
                        "DoNotDestroy"
                      ],
                      "type": "string"
                    }
                  },
                  "required": [
                    "providerRef",
                    "resource"
                  ],
                  "type": "object"
                },
                "status": {
                  "properties": {
                    "conditions": {
                      "items": {
                        "properties": {
                          "lastTransitionTime": {
                            "format": "date-time",
                            "type": "string"
                          },
                          "message": {
                            "type": "string"
                          },
                          "observedGeneration": {
                            "format": "int64",
                            "type": "integer"
                          },
                          "reason": {
                            "type": "string"
                          },
                          "status": {
                            "type": "string"
                          },
                          "type": {
                            "type": "string"
                          }
                        },
                        "required": [
                          "lastTransitionTime",
                          "message",
                          "reason",
                          "status",
                          "type"
                        ],
                        "type": "object"
                      },
                      "type": "array"
                    },
                    "observedGeneration": {
                      "format": "int64",
                      "type": "integer"
                    },
                    "phase": {
                      "type": "string"
                    }
                  },
                  "type": "object"
                }
              },
              "type": "object"
            }
          },
          "served": true,
          "storage": true,
          "subresources": {
            "status": {}
          }
        }
      ]
    }
  },
  {
    "apiVersion": "apiextensions.k8s.io/v1",
    "kind": "CustomResourceDefinition",
    "metadata": {
      "annotations": {
        "helm.sh/resource-policy": "keep"
      },
      "creationTimestamp": null,
      "labels": {
        "app.kubernetes.io/name": "google.kubeform.com",
        "app.kubernetes.io/part-of": "kubeform.com"
      },
      "name": "iampolicies.organization.google.kubeform.com"
    },
    "spec": {
      "group": "organization.google.kubeform.com",
      "names": {
        "kind": "IamPolicy",
        "listKind": "IamPolicyList",
        "plural": "iampolicies",
        "singular": "iampolicy"
      },
      "scope": "Namespaced",
      "versions": [
        {
          "additionalPrinterColumns": [
            {
              "jsonPath": ".status.phase",
              "name": "Phase",
              "type": "string"
            }
          ],
          "name": "v1alpha1",
          "schema": {
            "openAPIV3Schema": {
              "properties": {
                "apiVersion": {
                  "type": "string"
                },
                "kind": {
                  "type": "string"
                },
                "metadata": {
                  "type": "object"
                },
                "spec": {
                  "properties": {
                    "backendRef": {
                      "properties": {
                        "name": {
                          "type": "string"
                        }
                      },
                      "type": "object"
                    },
                    "providerRef": {
                      "properties": {
                        "name": {
                          "type": "string"
                        }
                      },
                      "type": "object"
                    },
                    "resource": {
                      "properties": {
                        "etag": {
                          "type": "string"
                        },
                        "id": {
                          "type": "string"
                        },
                        "orgID": {
                          "type": "string"
                        },
                        "policyData": {
                          "type": "string"
                        }
                      },
                      "required": [
                        "orgID",
                        "policyData"
                      ],
                      "type": "object"
                    },
                    "state": {
                      "properties": {
                        "etag": {
                          "type": "string"
                        },
                        "id": {
                          "type": "string"
                        },
                        "orgID": {
                          "type": "string"
                        },
                        "policyData": {
                          "type": "string"
                        }
                      },
                      "required": [
                        "orgID",
                        "policyData"
                      ],
                      "type": "object"
                    },
                    "terminationPolicy": {
                      "enum": [
                        "Delete",
                        "DoNotTerminate"
                      ],
                      "type": "string"
                    },
                    "updatePolicy": {
                      "enum": [
                        "Destroy",
                        "DoNotDestroy"
                      ],
                      "type": "string"
                    }
                  },
                  "required": [
                    "providerRef",
                    "resource"
                  ],
                  "type": "object"
                },
                "status": {
                  "properties": {
                    "conditions": {
                      "items": {
                        "properties": {
                          "lastTransitionTime": {
                            "format": "date-time",
                            "type": "string"
                          },
                          "message": {
                            "type": "string"
                          },
                          "observedGeneration": {
                            "format": "int64",
                            "type": "integer"
                          },
                          "reason": {
                            "type": "string"
                          },
                          "status": {
                            "type": "string"
                          },
                          "type": {
                            "type": "string"
                          }
                        },
                        "required": [
                          "lastTransitionTime",
                          "message",
                          "reason",
                          "status",
                          "type"
                        ],
                        "type": "object"
                      },
                      "type": "array"
                    },
                    "observedGeneration": {
                      "format": "int64",
                      "type": "integer"
                    },
                    "phase": {
                      "type": "string"
                    }
                  },
                  "type": "object"
                }
              },
              "type": "object"
            }
          },
          "served": true,
          "storage": true,
          "subresources": {
            "status": {}
          }
        }
      ]
    }
  },
  {
    "apiVersion": "apiextensions.k8s.io/v1",
    "kind": "CustomResourceDefinition",
    "metadata": {
      "annotations": {
        "helm.sh/resource-policy": "keep"
      },
      "creationTimestamp": null,
      "labels": {
        "app.kubernetes.io/name": "google.kubeform.com",
        "app.kubernetes.io/part-of": "kubeform.com"
      },
      "name": "policies.organization.google.kubeform.com"
    },
    "spec": {
      "group": "organization.google.kubeform.com",
      "names": {
        "kind": "Policy",
        "listKind": "PolicyList",
        "plural": "policies",
        "singular": "policy"
      },
      "scope": "Namespaced",
      "versions": [
        {
          "additionalPrinterColumns": [
            {
              "jsonPath": ".status.phase",
              "name": "Phase",
              "type": "string"
            }
          ],
          "name": "v1alpha1",
          "schema": {
            "openAPIV3Schema": {
              "properties": {
                "apiVersion": {
                  "type": "string"
                },
                "kind": {
                  "type": "string"
                },
                "metadata": {
                  "type": "object"
                },
                "spec": {
                  "properties": {
                    "backendRef": {
                      "properties": {
                        "name": {
                          "type": "string"
                        }
                      },
                      "type": "object"
                    },
                    "providerRef": {
                      "properties": {
                        "name": {
                          "type": "string"
                        }
                      },
                      "type": "object"
                    },
                    "resource": {
                      "properties": {
                        "booleanPolicy": {
                          "properties": {
                            "enforced": {
                              "type": "boolean"
                            }
                          },
                          "required": [
                            "enforced"
                          ],
                          "type": "object"
                        },
                        "constraint": {
                          "type": "string"
                        },
                        "etag": {
                          "type": "string"
                        },
                        "id": {
                          "type": "string"
                        },
                        "listPolicy": {
                          "properties": {
                            "allow": {
                              "properties": {
                                "all": {
                                  "type": "boolean"
                                },
                                "values": {
                                  "items": {
                                    "type": "string"
                                  },
                                  "type": "array"
                                }
                              },
                              "type": "object"
                            },
                            "deny": {
                              "properties": {
                                "all": {
                                  "type": "boolean"
                                },
                                "values": {
                                  "items": {
                                    "type": "string"
                                  },
                                  "type": "array"
                                }
                              },
                              "type": "object"
                            },
                            "inheritFromParent": {
                              "type": "boolean"
                            },
                            "suggestedValue": {
                              "type": "string"
                            }
                          },
                          "type": "object"
                        },
                        "orgID": {
                          "type": "string"
                        },
                        "restorePolicy": {
                          "properties": {
                            "default": {
                              "type": "boolean"
                            }
                          },
                          "required": [
                            "default"
                          ],
                          "type": "object"
                        },
                        "timeouts": {
                          "properties": {
                            "create": {
                              "format": "int64",
                              "type": "integer"
                            },
                            "default": {
                              "format": "int64",
                              "type": "integer"
                            },
                            "delete": {
                              "format": "int64",
                              "type": "integer"
                            },
                            "read": {
                              "format": "int64",
                              "type": "integer"
                            },
                            "update": {
                              "format": "int64",
                              "type": "integer"
                            }
                          },
                          "type": "object"
                        },
                        "updateTime": {
                          "type": "string"
                        },
                        "version": {
                          "format": "int64",
                          "type": "integer"
                        }
                      },
                      "required": [
                        "constraint",
                        "orgID"
                      ],
                      "type": "object"
                    },
                    "state": {
                      "properties": {
                        "booleanPolicy": {
                          "properties": {
                            "enforced": {
                              "type": "boolean"
                            }
                          },
                          "required": [
                            "enforced"
                          ],
                          "type": "object"
                        },
                        "constraint": {
                          "type": "string"
                        },
                        "etag": {
                          "type": "string"
                        },
                        "id": {
                          "type": "string"
                        },
                        "listPolicy": {
                          "properties": {
                            "allow": {
                              "properties": {
                                "all": {
                                  "type": "boolean"
                                },
                                "values": {
                                  "items": {
                                    "type": "string"
                                  },
                                  "type": "array"
                                }
                              },
                              "type": "object"
                            },
                            "deny": {
                              "properties": {
                                "all": {
                                  "type": "boolean"
                                },
                                "values": {
                                  "items": {
                                    "type": "string"
                                  },
                                  "type": "array"
                                }
                              },
                              "type": "object"
                            },
                            "inheritFromParent": {
                              "type": "boolean"
                            },
                            "suggestedValue": {
                              "type": "string"
                            }
                          },
                          "type": "object"
                        },
                        "orgID": {
                          "type": "string"
                        },
                        "restorePolicy": {
                          "properties": {
                            "default": {
                              "type": "boolean"
                            }
                          },
                          "required": [
                            "default"
                          ],
                          "type": "object"
                        },
                        "timeouts": {
                          "properties": {
                            "create": {
                              "format": "int64",
                              "type": "integer"
                            },
                            "default": {
                              "format": "int64",
                              "type": "integer"
                            },
                            "delete": {
                              "format": "int64",
                              "type": "integer"
                            },
                            "read": {
                              "format": "int64",
                              "type": "integer"
                            },
                            "update": {
                              "format": "int64",
                              "type": "integer"
                            }
                          },
                          "type": "object"
                        },
                        "updateTime": {
                          "type": "string"
                        },
                        "version": {
                          "format": "int64",
                          "type": "integer"
                        }
                      },
                      "required": [
                        "constraint",
                        "orgID"
                      ],
                      "type": "object"
                    },
                    "terminationPolicy": {
                      "enum": [
                        "Delete",
                        "DoNotTerminate"
                      ],
                      "type": "string"
                    },
                    "updatePolicy": {
                      "enum": [
                        "Destroy",
                        "DoNotDestroy"
                      ],
                      "type": "string"
                    }
                  },
                  "required": [
                    "providerRef",
                    "resource"
                  ],
                  "type": "object"
                },
                "status": {
                  "properties": {
                    "conditions": {
                      "items": {
                        "properties": {
                          "lastTransitionTime": {
                            "format": "date-time",
                            "type": "string"
                          },
                          "message": {
                            "type": "string"
                          },
                          "observedGeneration": {
                            "format": "int64",
                            "type": "integer"
                          },
                          "reason": {
                            "type": "string"
                          },
                          "status": {
                            "type": "string"
                          },
                          "type": {
                            "type": "string"
                          }
                        },
                        "required": [
                          "lastTransitionTime",
                          "message",
                          "reason",
                          "status",
                          "type"
                        ],
                        "type": "object"
                      },
                      "type": "array"
                    },
                    "observedGeneration": {
                      "format": "int64",
                      "type": "integer"
                    },
                    "phase": {
                      "type": "string"
                    }
                  },
                  "type": "object"
                }
              },
              "type": "object"
            }
          },
          "served": true,
          "storage": true,
          "subresources": {
            "status": {}
          }
        }
      ]
    }
  },
  {
    "apiVersion": "rbac.authorization.k8s.io/v1",
    "kind": "ClusterRole",
    "metadata": {
      "name": "appscode:metrics:edit",
      "labels": {
        "rbac.authorization.k8s.io/aggregate-to-admin": "true",
        "rbac.authorization.k8s.io/aggregate-to-edit": "true"
      },
      "annotations": {
        "helm.sh/hook": "pre-install,pre-upgrade",
        "helm.sh/hook-delete-policy": "before-hook-creation"
      }
    },
    "rules": [
      {
        "apiGroups": [
          "metrics.appscode.com"
        ],
        "resources": [
          "*"
        ],
        "verbs": [
          "*"
        ]
      }
    ]
  },
  {
    "kind": "ClusterRole",
    "apiVersion": "rbac.authorization.k8s.io/v1",
    "metadata": {
      "name": "appscode:metrics:view",
      "labels": {
        "rbac.authorization.k8s.io/aggregate-to-view": "true"
      },
      "annotations": {
        "helm.sh/hook": "pre-install,pre-upgrade",
        "helm.sh/hook-delete-policy": "before-hook-creation"
      }
    },
    "rules": [
      {
        "apiGroups": [
          "metrics.appscode.com"
        ],
        "resources": [
          "*"
        ],
        "verbs": [
          "get",
          "list",
          "watch"
        ]
      }
    ]
  }
]